http_helper/__init__.py
http_helper/client/__init__.py
http_helper/client/async_proxy.py
http_helper/utils/__init__.py
http_helper/utils/http_execption.py
http_helper/utils/log.py
http_helper/utils/reponse_handle_utils.py
python_http_helper-0.2.4.dist-info/licenses/LICENSE
python_http_helper-0.2.4.dist-info/METADATA
python_http_helper-0.2.4.dist-info/WHEEL
python_http_helper-0.2.4.dist-info/top_level.txt
python_http_helper-0.2.4.dist-info/RECORD
