Metadata-Version: 2.4
Name: python_http_helper
Version: 0.2.4
Summary: http helper python package
Author-email: ckf10000 <ckf10000@sina.com>
License:                                  Apache License
Project-URL: Homepage, https://github.com/ckf10000/http-helper
Project-URL: Source, https://github.com/ckf10000/http-helper
Project-URL: Issues, https://github.com/ckf10000/http-helper/issues
Requires-Python: >=3.12
License-File: LICENSE
Requires-Dist: aiohttp==3.13.2; python_version >= "3.12"
Requires-Dist: yarl==1.22.0; python_version >= "3.12"
Dynamic: license-file
